astream/__init__.py
astream/closeable_queue.py
astream/event_like.py
astream/experimental/__init__.py
astream/experimental/ala_env
astream/experimental/braille.py
astream/experimental/braille.svg
astream/experimental/braille_demo.py
astream/experimental/compose.py
astream/experimental/fun_with_unicode_braille.md
astream/experimental/miscutils/__init__.py
astream/experimental/mypy_stuff.py
astream/experimental/partializer.py
astream/experimental/pyre_stuff.py
astream/experimental/rdh_toolkit.py
astream/experimental/rich_charts.py
astream/experimental/rich_stream.py
astream/experimental/simple_surrogate.py
astream/experimental/stream_grouper.py
astream/experimental/stream_visualizer.py
astream/experimental/subproc.py
astream/experimental/timedeque.py
astream/experimental/transformer_utils.py
astream/experimental/worker_pool.py
astream/integrations/__init__.py
astream/integrations/sqlite.py
astream/integrations/zstd.py
astream/on_time.py
astream/pure.py
astream/sentinel.py
astream/sinks.py
astream/sources.py
astream/stream.py
astream/stream_utils.py
astream/transformers/__init__.py
astream/transformers/aggregators.py
astream/uptodate.py
astream/utils.py
astream/worker_q.py
astream-0.7.3.dist-info/WHEEL
astream-0.7.3.dist-info/METADATA
astream-0.7.3.dist-info/RECORD
